anonfiles_uploader/__init__.py
anonfiles_uploader-1.0.1.dist-info/LICENSE
anonfiles_uploader-1.0.1.dist-info/METADATA
anonfiles_uploader-1.0.1.dist-info/WHEEL
anonfiles_uploader-1.0.1.dist-info/top_level.txt
anonfiles_uploader-1.0.1.dist-info/RECORD
