Metadata-Version: 2.1
Name: anonfiles-uploader
Version: 1.0.1
Summary: Easily upload files to anonfiles.
Home-page: https://github.com/Ruu3f/anonfiles_uploader
Author: Ruu3f
License: CC0-1.0
Project-URL: Source, https://github.com/Ruu3f/anonfiles_uploader
Keywords: anonfiles,file-host,api-wrapper,file-hosting,file-uploader
Classifier: Development Status :: 5 - Production/Stable
Classifier: Intended Audience :: Developers
Classifier: License :: CC0 1.0 Universal (CC0 1.0) Public Domain Dedication
Classifier: Natural Language :: English
Classifier: Programming Language :: Python :: 3
Classifier: Programming Language :: Python :: 3.6
Classifier: Programming Language :: Python :: 3.7
Classifier: Programming Language :: Python :: 3.8
Classifier: Programming Language :: Python :: 3.9
Classifier: Programming Language :: Python :: 3.10
Classifier: Programming Language :: Python :: 3.11
Classifier: Programming Language :: Python :: Implementation :: CPython
Classifier: Programming Language :: Python :: Implementation :: PyPy
Requires-Python: >=3.6
License-File: LICENSE
Requires-Dist: aiohttp
